cofmpy/VERSION
cofmpy/__init__.py
cofmpy-0.2.0.dist-info/licenses/LICENSE
cofmpy-0.2.0.dist-info/METADATA
cofmpy-0.2.0.dist-info/WHEEL
cofmpy-0.2.0.dist-info/entry_points.txt
cofmpy-0.2.0.dist-info/top_level.txt
cofmpy-0.2.0.dist-info/RECORD
